odoo/addons/l10n_ch_isrb/README.rst
odoo/addons/l10n_ch_isrb/__init__.py
odoo/addons/l10n_ch_isrb/__manifest__.py
odoo/addons/l10n_ch_isrb/i18n/l10n_ch_isrb.pot
odoo/addons/l10n_ch_isrb/models/__init__.py
odoo/addons/l10n_ch_isrb/models/account_invoice.py
odoo/addons/l10n_ch_isrb/models/res_partner_bank.py
odoo/addons/l10n_ch_isrb/readme/DESCRIPTION.rst
odoo/addons/l10n_ch_isrb/static/description/icon.png
odoo/addons/l10n_ch_isrb/static/description/index.html
odoo/addons/l10n_ch_isrb/tests/__init__.py
odoo/addons/l10n_ch_isrb/tests/test_gen_isr_reference.py
odoo/addons/l10n_ch_isrb/views/res_partner_bank.xml
odoo13_addon_l10n_ch_isrb-13.0.1.0.1.dev4.dist-info/METADATA
odoo13_addon_l10n_ch_isrb-13.0.1.0.1.dev4.dist-info/WHEEL
odoo13_addon_l10n_ch_isrb-13.0.1.0.1.dev4.dist-info/top_level.txt
odoo13_addon_l10n_ch_isrb-13.0.1.0.1.dev4.dist-info/RECORD
